RetroUFO/RetroUFO.py
RetroUFO/RetroUFO_GUI.py
RetroUFO/__init__.py
RetroUFO-0.9.5.post1.dist-info/LICENSE
RetroUFO-0.9.5.post1.dist-info/METADATA
RetroUFO-0.9.5.post1.dist-info/WHEEL
RetroUFO-0.9.5.post1.dist-info/entry_points.txt
RetroUFO-0.9.5.post1.dist-info/top_level.txt
RetroUFO-0.9.5.post1.dist-info/RECORD
