Metadata-Version: 2.1
Name: RetroUFO
Version: 0.9.5.post1
Summary: Easily upgrade all libreto cores from the build bot
Home-page: https://github.com/Melon-Bread/RetroUFO
Author: Melon Bread
Author-email: rain@melonbread.dev
License: MIT
Keywords: libretro,retroarch,core
Platform: UNKNOWN
Classifier: Programming Language :: Python :: 3
Classifier: License :: OSI Approved :: MIT License
Classifier: Operating System :: OS Independent
Requires-Python: >=3.6
Requires-Dist: PySide2
